virtualcity/__init__.py
virtualcity-0.0.5.dist-info/METADATA
virtualcity-0.0.5.dist-info/WHEEL
virtualcity-0.0.5.dist-info/top_level.txt
virtualcity-0.0.5.dist-info/RECORD
