Metadata-Version: 2.1
Name: virtualcity
Version: 0.0.5
Summary: Python API to communicate with the VirtualCity environment
Home-page: https://github.com/ShuangLI59/virtualcity-python-api
Author: Shuang Li, Kabir Swain
Author-email: lishuang@mit.edu, kswain98@icloud.com
License: UNKNOWN
Project-URL: Documentation, https://virtualcity.readthedocs.io/en/latest/
Project-URL: Bug Tracker, https://github.com/ShuangLI59/virtualcity-python-api
Platform: UNKNOWN
Classifier: Programming Language :: Python :: 3
Classifier: License :: OSI Approved :: MIT License
Classifier: Operating System :: OS Independent
Requires-Python: >=3.8
Requires-Dist: numpy
Requires-Dist: gym
Requires-Dist: ray
Requires-Dist: tensorboardX
Requires-Dist: wandb
Requires-Dist: stable-baselines3
Requires-Dist: python-socketio
